{"mappings": [{"item": {"url": "recipes/", "title": "Cookbook"}, "tags": ["cookbook"]}, {"item": {"url": "recipes/add-kuira-to-an-android-project/", "title": "Add Kuira to an Android project"}, "tags": ["hilt", "integration", "setup"]}, {"item": {"url": "recipes/back-up-wallet-across-devices/", "title": "Back up your wallet across devices"}, "tags": ["backup", "drive", "dust", "wallet"]}, {"item": {"url": "recipes/bind-your-app-to-a-passkey-domain/", "title": "Bind your app to a passkey domain"}, "tags": ["assetlinks", "identity", "passkey", "signing"]}, {"item": {"url": "recipes/deploy-and-call-a-compact-contract/", "title": "Deploy and call a Compact contract"}, "tags": ["circuits", "compact", "contracts", "proving"]}, {"item": {"url": "recipes/hello-compact/", "title": "Hello Compact \u2014 write your first contract"}, "tags": ["compact", "contracts", "hello-world"]}, {"item": {"url": "recipes/run-kuira-doctor/", "title": "Run kuiraDoctor before each release"}, "tags": ["doctor", "preflight", "release", "troubleshooting"]}, {"item": {"url": "recipes/set-up-sigil-identity/", "title": "Set up Sigil identity"}, "tags": ["identity", "passkey", "sigil"]}]}